CMakeLists.txt
LICENSE.txt
MANIFEST.in
README.md
setup.py
./python/__init__.py
libmcc_lidar/Algorithm.cpp
libmcc_lidar/Algorithm.h
libmcc_lidar/AsciiGrid.h
libmcc_lidar/BinaryFile.cpp
libmcc_lidar/BinaryFile.h
libmcc_lidar/CMakeLists.txt
libmcc_lidar/Cell.h
libmcc_lidar/CellBlock.h
libmcc_lidar/Coordinate.h
libmcc_lidar/CoordinateInterval.cpp
libmcc_lidar/CoordinateInterval.h
libmcc_lidar/DisjointRegions.cpp
libmcc_lidar/DisjointRegions.h
libmcc_lidar/DuplicatePoints.cpp
libmcc_lidar/DuplicatePoints.h
libmcc_lidar/FindLibLAS.cmake
libmcc_lidar/Geometry3D.cpp
libmcc_lidar/Geometry3D.h
libmcc_lidar/Grid.h
libmcc_lidar/GridBase.cpp
libmcc_lidar/GridBase.h
libmcc_lidar/IClassificationVector.h
libmcc_lidar/IDataFormat.h
libmcc_lidar/IInterpolationRegion.h
libmcc_lidar/IPoint.h
libmcc_lidar/IPointVector.h
libmcc_lidar/IRasterSurface.h
libmcc_lidar/IRegionGenerator.h
libmcc_lidar/ISurfaceInterpolation.h
libmcc_lidar/IUnclassifiedPoints.h
libmcc_lidar/IXyzPointReader.h
libmcc_lidar/InterpolationRegion.cpp
libmcc_lidar/InterpolationRegion.h
libmcc_lidar/LasDataFormat.cpp
libmcc_lidar/LasDataFormat.h
libmcc_lidar/LasDataReader.cpp
libmcc_lidar/LasDataReader.h
libmcc_lidar/LasXyzPoint.h
libmcc_lidar/LineIndent.cpp
libmcc_lidar/LineIndent.h
libmcc_lidar/LocaleUtilities.cpp
libmcc_lidar/LocaleUtilities.h
libmcc_lidar/OutputCsvFile.cpp
libmcc_lidar/OutputCsvFile.h
libmcc_lidar/Point.h
libmcc_lidar/PointCanopyHeightFile.cpp
libmcc_lidar/PointCanopyHeightFile.h
libmcc_lidar/PointClassification.h
libmcc_lidar/PointCsvFile.cpp
libmcc_lidar/PointCsvFile.h
libmcc_lidar/PointIO.cpp
libmcc_lidar/PointIO.h
libmcc_lidar/PointSelector.h
libmcc_lidar/PointVector.cpp
libmcc_lidar/PointVector.h
libmcc_lidar/PointVectorIterator.h
libmcc_lidar/PointVectorIteratorImpl.h
libmcc_lidar/ProgramExceptions.h
libmcc_lidar/ProgramParameters.cpp
libmcc_lidar/ProgramParameters.h
libmcc_lidar/ProgressBar.cpp
libmcc_lidar/ProgressBar.h
libmcc_lidar/README.txt
libmcc_lidar/RasterSurface.cpp
pymcc_lidar.egg-info/PKG-INFO
pymcc_lidar.egg-info/SOURCES.txt
pymcc_lidar.egg-info/dependency_links.txt
pymcc_lidar.egg-info/requires.txt
pymcc_lidar.egg-info/top_level.txt
