Metadata-Version: 1.1
Name: pymcc-lidar
Version: 1.3
Summary: A Python package for point cloud classification using relative height
Home-page: https://github.com/stgl/pymcc
Author: ['George Hilley', 'Robert Sare']
Author-email: hilley@stanford.edu
License: MIT
Platform: UNKNOWN
Classifier: Development Status :: 4 - Beta
Classifier: Intended Audience :: Developers
Classifier: Intended Audience :: Science/Research
Classifier: Programming Language :: Python :: 3
Classifier: License :: OSI Approved :: MIT License
Classifier: Operating System :: OS Independent
